multicode/__init__.py
multicode/__main__.py
multicode/util.py
multicode/data/confusables/basic.tsv
multicode/data/confusables/epa.tsv
multicode/data/confusables/ipa.tsv
multicode/data/confusables/metadata.json
multicode/data/thirdparty/confusablesSummary.txt
multicode-0.2.1.dist-info/LICENSE
multicode-0.2.1.dist-info/METADATA
multicode-0.2.1.dist-info/WHEEL
multicode-0.2.1.dist-info/entry_points.txt
multicode-0.2.1.dist-info/top_level.txt
multicode-0.2.1.dist-info/RECORD
